xfloweltsourcebase/__init__.py
xfloweltsourcebase/base/__init__.py
xfloweltsourcebase/base/auth.py
xfloweltsourcebase/base/constants.py
xfloweltsourcebase/base/data_sink.py
xfloweltsourcebase/base/events.py
xfloweltsourcebase/base/exceptions.py
xfloweltsourcebase/base/extractor_base.py
xfloweltsourcebase/base/utils.py
xfloweltsourcebase/github/__init__.py
xfloweltsourcebase/github/branch_extractor.py
xfloweltsourcebase/github/commit_comment_extractor.py
xfloweltsourcebase/github/commit_detail_extractor.py
xfloweltsourcebase/github/commit_extractor.py
xfloweltsourcebase/github/commit_status_extractor.py
xfloweltsourcebase/github/github_events.py
xfloweltsourcebase/github/github_exceptions.py
xfloweltsourcebase/github/issue_comment_extractor.py
xfloweltsourcebase/github/issue_event_extractor.py
xfloweltsourcebase/github/issue_extractor.py
xfloweltsourcebase/github/member_extractor.py
xfloweltsourcebase/github/pull_comment_extractor.py
xfloweltsourcebase/github/pull_commit_extractor.py
xfloweltsourcebase/github/pull_detail_extractor.py
xfloweltsourcebase/github/pull_extractor.py
xfloweltsourcebase/github/pull_review_extractor.py
xfloweltsourcebase/github/repo_extractor.py
xfloweltsourcebase/github/repo_team_extractor.py
xfloweltsourcebase/github/team_extractor.py
xfloweltsourcebase/github/team_member_extractor.py
xfloweltsourcebase/github/user_repo_extractor.py
xfloweltsourcebase/jira/__init__.py
xfloweltsourcebase/jira/board_extractor.py
xfloweltsourcebase/jira/board_issue_extractor.py
xfloweltsourcebase/jira/custom_field_extractor.py
xfloweltsourcebase/jira/dashboard_extractor.py
xfloweltsourcebase/jira/epic_extractor.py
xfloweltsourcebase/jira/group_extractor.py
xfloweltsourcebase/jira/issue_comment_extractor.py
xfloweltsourcebase/jira/issue_extractor.py
xfloweltsourcebase/jira/jira_events.py
xfloweltsourcebase/jira/project_extractor.py
xfloweltsourcebase/jira/sprint_extractor.py
xfloweltsourcebase/jira/sprint_issue_extractor.py
xfloweltsourcebase-1.0.1.dist-info/METADATA
xfloweltsourcebase-1.0.1.dist-info/WHEEL
xfloweltsourcebase-1.0.1.dist-info/top_level.txt
xfloweltsourcebase-1.0.1.dist-info/RECORD
