Metadata-Version: 2.1
Name: xfloweltsourcebase
Version: 1.0.1
Summary: ExperienceFlow API based sources
Author: Tongguo Pang
Author-email: tongguo@experienceflow.ai
License: MIT
Requires-Dist: httpx (>=0.23.0)
Provides-Extra: tests
Requires-Dist: pytest (>=7.2.0) ; extra == 'tests'
Requires-Dist: pytest-mock (==3.10.0) ; extra == 'tests'
Requires-Dist: pytest-cov (==6.5.0) ; extra == 'tests'
Requires-Dist: pytest-httpx (==0.21.2) ; extra == 'tests'
